Workbook

Sheet Income Statement
B1: (In USD millions)
A2: Year | B2: Revenue | C2: Cost of Revenue | D2: Gross Profit | E2: R & D Exp | F2: Sales & Marketing Exp | G2: General & Admin Exp | H2: Operating Income | I2: Net Income
A3: 2021 | B3: 168088 | C3: 52232 | D3: 115856 | E3: 20716 | F3: 20117 | G3: 5107 | H3: 69916 | I3: 61271
A4: 2022 | B4: 198270 | C4: 62650 | D4: 315620 | E4: 24512 | F4: 21825 | G4: 5900 | H4: 83383 | I4: 72738
A5: 2023 | B5: 211915 | C5: 65863 | D5: 146052 | E5: 27195 | F5: 22759 | G5: 7575 | H5: 88523 | I5: 72361
A6: 2024 | B6: 245122 | C6: 74114 | D6: 171008 | E6: 29510 | F6: 24456 | G6: 7609 | H6: 109433 | I6: 88136
A7: 2025 | B7: 281724 | C7: 87831 | D7: 193893 | E7: 32488 | F7: 25654 | G7: 7223 | H7: 128528 | I7: 101832
A8: 2020 | B8: 143015 | C8: NA | D8: NA | E8: NA | F8: NA | G8: NA | H8: NA | I8: 44281

Sheet Balance Sheet
B1: (In USD millions)
A2: Year | B2: Cash and Cash eq. | C2: Total Assets | D2: Total Liability | E2: Total Debt | F2: Shareholder's Equity
A3: 2021 | B3: 14224 | C3: 333779 | D3: 191791 | E3: 103134 | F3: 141988
A4: 2022 | B4: 13931 | C4: 364840 | D4: 198298 | E4: 103216 | F4: 166542
A5: 2023 | B5: 34704 | C5: 411976 | D5: 205753 | E5: 101604 | F5: 206223
A6: 2024 | B6: 18315 | C6: 512163 | D6: 243686 | E6: 118400 | F6: 268477
A7: 2025 | B7: 30242 | C7: 619003 | D7: 275524 | E7: 134306 | F7: 343479
A8: 2020 | B8: NA | C8: 301331 | D8: NA | E8: NA | F8: NA

Sheet Cash Flow Statement
B1: (In USD millions)
A2: Year | B2: Operating Cash Flow | C2: Cap Ex
A3: 2021 | B3: 76740 | C3: 20622
A4: 2022 | B4: 89035 | C4: 23886
A5: 2023 | B5: 87582 | C5: 28107
A6: 2024 | B6: 118548 | C6: 44477
A7: 2025 | B7: 136162 | C7: 64551

Sheet Segment Revenue
C1: Revenue(In USD Millions) | J1: Operating Income(In USD Millions)
A2: Year | B2: Productivity and Business Processes | C2: Intelligent Cloud | D2: More Personal Computing | E2: Total | H2: Year | I2: Productivity and Business Processes | J2: Intelligent Cloud | K2: More Personal Computing | L2: Total
A3: 2021 | B3: 53915 | C3: 60080 | D3: 54093 | E3: =SUM(B3:D3) -> 168088 | H3: 2021 | I3: 24351 | J3: 26126 | K3: 19439 | L3: =SUM(I3:K3) -> 69916
A4: 2022 | B4: 63364 | C4: 74965 | D4: 59941 | E4: =SUM(B4:D4) -> 198270 | H4: 2022 | I4: 29690 | J4: 33203 | K4: 20490 | L4: =SUM(I4:K4) -> 83383
A5: 2023 | B5: 69274 | C5: 87907 | D5: 54734 | E5: =SUM(B5:D5) -> 211915 | H5: 2023 | I5: 34189 | J5: 37884 | K5: 16450 | L5: =SUM(I5:K5) -> 88523
A6: 2024 | B6: 77728 | C6: 105362 | D6: 62032 | E6: =SUM(B6:D6) -> 245122 | H6: 2024 | I6: 40540 | J6: 49584 | K6: 19309 | L6: =SUM(I6:K6) -> 109433
A7: 2025 | B7: 120810 | C7: 106265 | D7: 54649 | E7: =SUM(B7:D7) -> 281724 | H7: 2025 | I7: 69773 | J7: 44589 | K7: 14166 | L7: =SUM(I7:K7) -> 128528
A8: 2020 | B8: 46398 | C8: 48366 | D8: 48251 | E8: =SUM(B8:D8) -> 143015 | H8: 2020 | I8: 18724 | J8: 18324 | K8: 15911 | L8: =SUM(I8:K8) -> 52959

Sheet KPI's
B1: Year | C1: Revenue Growth % | D1: Gross Margin % | E1: Operating Margin % | F1: Net Income Growth % | G1: Net Margin % | H1: ROE % | I1: Debt to Equity | J1: Free Cash Flow | K1: FCF Margin % | L1: Asset Growth %
A2: Formulas | C2: (CY revenue- PY revenue)/ PY revenue | D2: Gross Profit/Revenue | E2: Oerating Income/Revenue | F2: (CY net Income- PY net Income)/PY net Income | G2: Net Income/ Revenue | H2: Net Income/SHF | I2: Total Debt/SHF | J2: Operating CF - Cap Ex | K2: FCF/Revenue | L2: (CY Assets- PY Assets)/PY assets
B4: 2021 | C4: =(('Income Statement'!B3-'Income Statement'!B8)/'Income Statement'!B8) -> 0.17531727 | D4: ='Income Statement'!D3/'Income Statement'!B3 -> 0.68925801 | E4: ='Income Statement'!H3/'Income Statement'!B3 -> 0.41594879 | F4: =('Income Statement'!I3-'Income Statement'!I8)/'Income Statement'!I3 -> 0.27729268 | G4: ='Income Statement'!I3/'Income Statement'!B3 -> 0.3645174 | H4: ='Income Statement'!I3/'Balance Sheet'!F3 -> 0.43152238 | I4: ='Balance Sheet'!E3/'Balance Sheet'!F3 -> 0.72635716 | J4: ='Cash Flow Statement'!B3-'Cash Flow Statement'!C3 -> 56118 | K4: =J4/'Income Statement'!B3 -> 0.33386083 | L4: =('Balance Sheet'!C3-'Balance Sheet'!C8)/'Balance Sheet'!C8 -> 0.10768225
B5: 2022 | C5: =('Income Statement'!B4-'Income Statement'!B3)/'Income Statement'!B3 -> 0.17956071 | D5: ='Income Statement'!D4/'Income Statement'!B4 -> 1.5918697 | E5: ='Income Statement'!H4/'Income Statement'!B4 -> 0.42055278 | F5: =('Income Statement'!I4-'Income Statement'!I3)/'Income Statement'!I3 -> 0.18715216 | G5: ='Income Statement'!I4/'Income Statement'!B4 -> 0.36686337 | H5: ='Income Statement'!I4/'Balance Sheet'!F4 -> 0.43675469 | I5: ='Balance Sheet'!E4/'Balance Sheet'!F4 -> 0.61975958 | J5: ='Cash Flow Statement'!B4-'Cash Flow Statement'!C4 -> 65149 | K5: =J5/'Income Statement'!B4 -> 0.32858728 | L5: =('Balance Sheet'!C4-'Balance Sheet'!C3)/'Balance Sheet'!C3 -> 0.093058581
B6: 2023 | C6: =('Income Statement'!B5-'Income Statement'!B4)/'Income Statement'!B4 -> 0.068820296 | D6: ='Income Statement'!D5/'Income Statement'!B5 -> 0.68920086 | E6: ='Income Statement'!H5/'Income Statement'!B5 -> 0.41772881 | F6: =('Income Statement'!I5-'Income Statement'!I4)/'Income Statement'!I4 -> -0.0051829855 | G6: ='Income Statement'!I5/'Income Statement'!B5 -> 0.34146238 | H6: ='Income Statement'!I5/'Balance Sheet'!F5 -> 0.35088715 | I6: ='Balance Sheet'!E5/'Balance Sheet'!F5 -> 0.49268995 | J6: ='Cash Flow Statement'!B5-'Cash Flow Statement'!C5 -> 59475 | K6: =J6/'Income Statement'!B5 -> 0.28065498 | L6: =('Balance Sheet'!C5-'Balance Sheet'!C4)/'Balance Sheet'!C4 -> 0.12919636
B7: 2024 | C7: =('Income Statement'!B6-'Income Statement'!B5)/'Income Statement'!B5 -> 0.15669962 | D7: ='Income Statement'!D6/'Income Statement'!B6 -> 0.69764444 | E7: ='Income Statement'!H6/'Income Statement'!B6 -> 0.446443 | F7: =('Income Statement'!I6-'Income Statement'!I5)/'Income Statement'!I5 -> 0.21800417 | G7: ='Income Statement'!I6/'Income Statement'!B6 -> 0.35955973 | H7: ='Income Statement'!I6/'Balance Sheet'!F6 -> 0.32828138 | I7: ='Balance Sheet'!E6/'Balance Sheet'!F6 -> 0.44100612 | J7: ='Cash Flow Statement'!B6-'Cash Flow Statement'!C6 -> 74071 | K7: =J7/'Income Statement'!B6 -> 0.30218014 | L7: =('Balance Sheet'!C6-'Balance Sheet'!C5)/'Balance Sheet'!C5 -> 0.2431865
B8: 2025 | C8: =('Income Statement'!B7-'Income Statement'!B6)/'Income Statement'!B6 -> 0.14932156 | D8: ='Income Statement'!D7/'Income Statement'!B7 -> 0.68823742 | E8: ='Income Statement'!H7/'Income Statement'!B7 -> 0.45621956 | F8: =('Income Statement'!I7-'Income Statement'!I6)/'Income Statement'!I6 -> 0.15539621 | G8: ='Income Statement'!I7/'Income Statement'!B7 -> 0.36146015 | H8: ='Income Statement'!I7/'Balance Sheet'!F7 -> 0.29647227 | I8: ='Balance Sheet'!E7/'Balance Sheet'!F7 -> 0.39101663 | J8: ='Cash Flow Statement'!B7-'Cash Flow Statement'!C7 -> 71611 | K8: =J8/'Income Statement'!B7 -> 0.2541885 | L8: =('Balance Sheet'!C7-'Balance Sheet'!C6)/'Balance Sheet'!C6 -> 0.20860546
D10: Segment Revenue Share % | I10: Segment Operating Income Share % | P10: Segment Revenue Growth %
A11: Formulas | D11: Segment Revenue/Total Revenue | I11: Segment Operating Inc/Total Operating Inc | P11: (CY Segment Rev- PY Segment Rev)/PY Segment Rev
B13: Year | C13: Productivity and Business Processes | D13: Intelligent Cloud | E13: More Personal Computing | H13: Year | I13: Productivity and Business Processes | J13: Intelligent Cloud | K13: More Personal Computing | N13: Year | O13: Productivity and Business Processes | P13: Intelligent Cloud | Q13: More Personal Computing
B14: 2021 | C14: ='Segment Revenue'!B3/'Income Statement'!B3 -> 0.3207546 | D14: ='Segment Revenue'!C3/'Income Statement'!B3 -> 0.35743182 | E14: ='Segment Revenue'!D3/'Income Statement'!B3 -> 0.32181357 | H14: 2021 | I14: ='Segment Revenue'!I3/'Income Statement'!H3 -> 0.34828938 | J14: ='Segment Revenue'!J3/'Income Statement'!H3 -> 0.37367698 | K14: ='Segment Revenue'!K3/'Income Statement'!H3 -> 0.27803364 | N14: 2021 | O14: =('Segment Revenue'!B3-'Segment Revenue'!B8)/'Segment Revenue'!B8 -> 0.16201129 | P14: =('Segment Revenue'!C3-'Segment Revenue'!C8)/'Segment Revenue'!C8 -> 0.24219493 | Q14: =('Segment Revenue'!D3-'Segment Revenue'!D8)/'Segment Revenue'!D8 -> 0.12107521
B15: 2022 | C15: ='Segment Revenue'!B4/'Income Statement'!B4 -> 0.31958441 | D15: ='Segment Revenue'!C4/'Income Statement'!B4 -> 0.37809553 | E15: ='Segment Revenue'!D4/'Income Statement'!B4 -> 0.30232007 | H15: 2022 | I15: ='Segment Revenue'!I4/'Income Statement'!H4 -> 0.35606778 | J15: ='Segment Revenue'!J4/'Income Statement'!H4 -> 0.39819867 | K15: ='Segment Revenue'!K4/'Income Statement'!H4 -> 0.24573354 | N15: 2022 | O15: =('Segment Revenue'!B4-'Segment Revenue'!B3)/'Segment Revenue'!B3 -> 0.17525735 | P15: =('Segment Revenue'!C4-'Segment Revenue'!C3)/'Segment Revenue'!C3 -> 0.247753 | Q15: =('Segment Revenue'!D4-'Segment Revenue'!D3)/'Segment Revenue'!D3 -> 0.10811011
B16: 2023 | C16: ='Segment Revenue'!B5/'Income Statement'!B5 -> 0.32689522 | D16: ='Segment Revenue'!C5/'Income Statement'!B5 -> 0.41482198 | E16: ='Segment Revenue'!D5/'Income Statement'!B5 -> 0.2582828 | H16: 2023 | I16: ='Segment Revenue'!I5/'Income Statement'!H5 -> 0.38621601 | J16: ='Segment Revenue'!J5/'Income Statement'!H5 -> 0.42795658 | K16: ='Segment Revenue'!K5/'Income Statement'!H5 -> 0.18582741 | N16: 2023 | O16: =('Segment Revenue'!B5-'Segment Revenue'!B4)/'Segment Revenue'!B4 -> 0.093270627 | P16: =('Segment Revenue'!C5-'Segment Revenue'!C4)/'Segment Revenue'!C4 -> 0.17264057 | Q16: =('Segment Revenue'!D5-'Segment Revenue'!D4)/'Segment Revenue'!D4 -> -0.086868754
B17: 2024 | C17: ='Segment Revenue'!B6/'Income Statement'!B6 -> 0.31709924 | D17: ='Segment Revenue'!C6/'Income Statement'!B6 -> 0.42983494 | E17: ='Segment Revenue'!D6/'Income Statement'!B6 -> 0.25306582 | H17: 2024 | I17: ='Segment Revenue'!I6/'Income Statement'!H6 -> 0.37045498 | J17: ='Segment Revenue'!J6/'Income Statement'!H6 -> 0.45309916 | K17: ='Segment Revenue'!K6/'Income Statement'!H6 -> 0.17644586 | N17: 2024 | O17: =('Segment Revenue'!B6-'Segment Revenue'!B5)/'Segment Revenue'!B5 -> 0.12203713 | P17: =('Segment Revenue'!C6-'Segment Revenue'!C5)/'Segment Revenue'!C5 -> 0.19856212 | Q17: =('Segment Revenue'!D6-'Segment Revenue'!D5)/'Segment Revenue'!D5 -> 0.13333577
B18: 2025 | C18: ='Segment Revenue'!B7/'Income Statement'!B7 -> 0.42882396 | D18: ='Segment Revenue'!C7/'Income Statement'!B7 -> 0.37719541 | E18: ='Segment Revenue'!D7/'Income Statement'!B7 -> 0.19398063 | H18: 2025 | I18: ='Segment Revenue'!I7/'Income Statement'!H7 -> 0.54286226 | J18: ='Segment Revenue'!J7/'Income Statement'!H7 -> 0.34692052 | K18: ='Segment Revenue'!K7/'Income Statement'!H7 -> 0.11021723 | N18: 2025 | O18: =('Segment Revenue'!B7-'Segment Revenue'!B6)/'Segment Revenue'!B6 -> 0.55426616 | P18: =('Segment Revenue'!C7-'Segment Revenue'!C6)/'Segment Revenue'!C6 -> 0.0085704523 | Q18: =('Segment Revenue'!D7-'Segment Revenue'!D6)/'Segment Revenue'!D6 -> -0.11901922

Sheet Dashboard Blueprint
H1: Dashboard Theme
H2: Microsoft FY2021–FY2025
H3: Evaluating Whether Microsoft's Strategic Investments Created Sustainable Shareholder Value
D5: PAGE 1 — WHY(Value Creation Overwiew) | F5: PAGE 2 — HOW (Growth Engine) | H5: PAGE 3 — HOW (Value Conversion Engine) | J5: PAGE 4 — HOW (Cash Realization Engine) | L5: PAGE 5 — WHAT
D7: Did Microsoft's Strategy Create Shareholder Value? | F7: How Did Microsoft Generate Growth? | H7: How Efficiently Was Growth Converted Into Profit? | J7: Were Profits Converted Into Cash? | L7: What Financial Position Did Microsoft Achieve?
D9: Context | F9: Context | H9: Context | J9: Context | L9: Context
D11: Over FY2021–FY2025, Microsoft invested significantly in Cloud and AI. The purpose of this analysis is to determine whether those investments translated into value for shareholders. | F11: Value cannot be created without growth. Understanding where growth originated helps identify the effectiveness of Microsoft's strategic priorities. | H11: Growth alone does not create shareholder value. The true test is whether the company can convert revenue into profitable earnings while managing costs effectively. | J11: Strong financial performance should ultimately result in strong cash generation. Cash validates the quality of earnings. | L11: The result of growth, profitability, and cash generation should be reflected in a stronger financial position and the ability to sustain future growth.
D13: KPIs | F13: KPIs | H13: KPIs | J13: KPIs | L13: KPIs
D15: Revenue | F15: Revenue Growth % | H15: Gross Profit | J15: Operating Cash Flow | L15: Total Assets
D16: Revenue Growth % | F16: Segment Revenue | H16: Gross Margin % | J16: Free Cash Flow | L16: Total Liabilities
D17: Net Income | F17: Segment Contribution % | H17: Operating Income | J17: FCF Margin % | L17: Shareholders' Equity
D18: Net Income Growth % | H18: Operating Margin % | L18: Debt-to-Equity
D19: Free Cash Flow | F19: Visuals | H19: Net Margin % | J19: Visuals | L19: ROE
D20: ROE | H20: Operating Expense Ratio
F21: Revenue Trend | J21: Operating Cash Flow Trend | L21: Visuals
D22: Visuals | F22: Segment Revenue Trend | H22: Visuals | J22: Free Cash Flow Trend
F23: Revenue Mix by Segment | J23: Net Income vs Free Cash Flow | L23: Assets vs Liabilities
D24: Revenue Trend | F24: Growth Contribution by Segment | H24: Margin Trend Analysis | J24: OCF vs Net Income Comparison | L24: Equity Growth Trend
D25: Net Income Trend | H25: Cost of Revenue Trend | L25: Debt-to-Equity Trend
D26: FCF Trend | F26: Data Used | H26: Operating Income Trend | J26: Data Used | L26: Financial Strength Scorecard
D27: KPI Cards | H27: P&L Waterfall
F28: Revenue | H28: Expense Breakdown | J28: Operating Cash Flow | L28: Data Used
D29: Key Message | F29: Productivity & Business Processes | J29: CapEx
F30: Intelligent Cloud | H30: Data Used | J30: Free Cash Flow | L30: Assets
D31: Microsoft's overall financial performance improved significantly over the five-year period, indicating substantial value creation. | F31: More Personal Computing | J31: Net Income | L31: Liabilities
H32: Revenue | L32: Equity
F33: Key Message | H33: Cost of Revenue | J33: Key Message | L33: Debt
H34: Gross Profit | L34: ROE
F35: Intelligent Cloud emerged as the primary driver of Microsoft's growth, gradually reshaping the company's revenue mix. | H35: Operating Income | J35: Microsoft's earnings were consistently supported by strong cash generation, demonstrating high earnings quality.
H36: R&D | L36: Key Message
H37: Sales & Marketing
H38: G&A | L38: Microsoft strengthened its financial foundation while expanding its business, positioning itself to continue investing in future opportunities.
H40: Key Message
H42: Microsoft successfully translated revenue growth into operating profitability while continuing to invest in innovation and expansion.

Sheet Narrative Flow
H2: WHY
G3: Message- | H3: Between FY2021 and FY2025, Microsoft made significant investments in Cloud and AI with the objective of creating long-term shareholder value. This analysis evaluates whether those investments delivered meaningful financial outcomes.
H4: Did Microsoft create shareholder value?
H5: ↓
H6: HOW
G7: Message- | H7: Microsoft's value creation journey began with sustained revenue growth, primarily driven by the increasing contribution of Intelligent Cloud and the evolution of its business mix.
H8: How was growth generated?
H9: ↓
H10: HOW
G11: Message- | H11: Growth alone does not create value. Microsoft strengthened value creation by efficiently converting revenue into operating profits while maintaining control over costs and supporting strategic investments.
H12: How was growth converted into profit?
H13: ↓
H14: HOW
G15: Message- | H15: The quality of Microsoft's financial performance is reflected in its ability to convert profits into cash, generating strong operating and free cash flows to support future investments and shareholder returns.
H16: How were profits converted into cash?
H17: ↓
H18: WHAT
G19: Message- | H19: The combined impact of growth, profitability, and cash generation resulted in a stronger financial position, reinforcing Microsoft's ability to sustain future growth and continue creating shareholder value.
H20: What financial position was ultimately achieved?
